{
  "summary": "\u2022 Having 9 years of IT experience in Object Oriented development, testing, and support of Enterprise\napplications using Java/J2EE technologies.\n\u2022 Extensive experience in core Java and Advanced Java frameworks such as Spring (MVC, IoC, AOP,\nSecurity, DI, JDBC), Servlets, ORM tools (Java Persistence API, Hibernate and MyBatis), along with\nother java technologies like EJB, Junit, Apache Struts 2, Apache Axis, JFC (SWING, AWT, Java 2D),\nJSTL and log4j.\n\u2022 Excellent Proficiency in frontend development using HTML, CSS, JavaScript, AngularJS, Backbone.js,\njQuery, Bootstrap, AJAX and Adobe Flash.\n\u2022 Expertise in developing and registering web services using JAX-RPC, JAX-WS, SAAJ, JAX-RS, SOAP,\nREST, WSDL, UDDI registry along with developing micro services and other middleware.\n\u2022 Extensive experience with building cloud based applications.\n\u2022 Has vast experience in relational databases like Oracle, MySQL, DB2, MongoDB, NoSQL, SQL and\nPL/SQL.\n\u2022 Successfully designed and developed Java Multi-Threading based collector parser and distributor process,\nwhen the requirement was to collect, parse and distribute the data coming at a speed of thousand messages per\nseconds.\n\u2022 Worked on MVC - Struts, JSF and spring framework.\n\u2022 Explored Spark, Kafka along with other open source projects to create a real time analytics framework.\n\u2022 Strong experience in developing and deploying applications through application servers like Apache Tomcat,\nIBM WebSphere, WebLogic and Jboss along with environments like Node.js.\n\u2022 Proficient with J2EE design patterns such as Session Facade, Service Locator, DAO, DTO, Value Object,\nFront Controller, Factory, Business Object, and Singleton.\n\u2022 Experienced with use case diagrams, activity diagrams, sequence diagrams and class diagrams using UML\nmodeling tools like Rational Rose and Visio.\n\u2022 Experience with JUnit, ANT, Jasmine and Maven scripts.\n\u2022 Defined and created various functional requirement documents and design specification documents after\nperforming requirement analysis for the systems to be developed and worked with bug tracking tools like\nJIRA\n\u2022 Implemented Micro-services using Pivotal Cloud Foundry platform build upon Spring Boot Services\n\u2022 Held responsibility for conceptual design, creation, and maintenance of system diagrams for development,\ntesting & production environments, taking part in review of use case, design, code, test and implementation\nplans while working on all phases of Software Development Life Cycle.\n\u2022 Excellent experience in building application with service-oriented-architecture (SOA).\n\u2022 Skilled at interacting with clients, collection of requirement specifications from the client site, performing\nrequirement analysis and designing.\n\u2022 Has strong analytical & creative problem solving abilities along with written and verbal communication,\ninterpersonal and presentation skills.\n\u2022 Handled multiple tasks while managing time efficiently, meeting deadlines, coordinating project schedules\nand releases, meeting with clients and addressing their concerns.\n\u2022 Has ability to quickly learn and apply new tools and technologies, translate algorithms and ideas into software\napplications.\n\u2022 Designed back-end solutions for large-scale, on-demand marketing systems.\n\u2022 Developed software using Jenkins integration service.\n\u2022 Worked with Adobe Flexto create expressive and interactive interfaces.\n\u2022 Extensive experience using XML and JSON as data interchange format for asynchronous requests along with\ngood experience working with XML, XSLT, XSD and JAXB.\n\u2022 Developed and deployed end-to-end enterprise applications using web technologies and enterprise\ntechnologies in client-server environment and distributed environments like 3-tier and N-tier architectures.\n\u2022 Worked on testing tools like JUnit for application integration testing and built highly scalable and high\nperforming web applications that support day-to-day operations.",
  "total_experience": 8,
  "skills": [
    "java",
    "designing",
    "Developed Maven",
    "Developed front end web pages",
    "Sr.Java/J2EE Developer\nDescription",
    "(Rational\nApplication Developer",
    "Developed custom tags",
    "all the developed modules",
    "lead/direct technical development teams",
    "Full stack development",
    "full\nstack development",
    "frontend development",
    "Developed JUnit test cases",
    "Web application development",
    "Test Driven Development",
    "Java/J2EE Developer\nDescription",
    "product development teams",
    "Developed software",
    "Developed messaging system",
    "Oracle SQL Developer",
    "\uf0b7 Developed Exception handling framework",
    "building application",
    "Java",
    "SQL Developer",
    "Developed DAO (Data Access Object) classes",
    "development",
    "developed specs",
    "Full Stack Java Developer\nDescription",
    "Pivotal Cloud Foundry platform build",
    "Adobe Flash\nSoftware development",
    "Designed and developed systems",
    "the Single Page Application development",
    "developed components",
    "Java Developer\nDescription",
    "MyBatis\nUI Development HTML",
    "JBuilder",
    "developers",
    "Java Full Stack Developer\nDescription",
    "Software development",
    "a R&D java developer",
    "Software Development Life Cycle",
    "Development",
    "test-first development",
    "Object Oriented development",
    "the application development"
  ],
  "companies": [
    "a speed of thousand messages per\nseconds.",
    "the\nErie plant, while engine manufacturing takes place in Grove City, Pennsylvania.",
    "interacting with clients, collection of requirement specifications from the client site, performing\nrequirement analysis and designing."
  ],
  "positions": [],
  "education": [
    "Bachelor\u2019s degree from JNTUH April 2008.",
    "TECHNICAL SKILLS:",
    "Eclipse, IBM RAD, JBuilder, NetBeans, MyEclipse, Dream Weaver, Surround",
    "SCM, Rational ClearCase, CVS, SVN, GIT, SublimeText, Rational ClearQuest,",
    "Software development and Rational Rose XDE, TOAD, Oracle SQL Developer, Mantis Bug Tracker, PuTTY,",
    "management tools WinSCP, Cygwin, Apache Ant, Apache Maven, MS Office, Drool, Enterprise",
    "Architect, Grunt, Bower, Jira, Webstorm, OEPE, STS, Spring Roo, Google Web",
    "Toolkit, Adobe Experience Manager",
    "Operating Systems Microsoft Windows, UNIX, LINUX, Solaris, Windows Server",
    "Junit, Log4j, Apache Struts 2, Spring, Hibernate, Apache Axis, Oracle WebLogic,",
    "JAVA frameworks and Apache Tiles, Servlets, JSP, JDBC, JMS, EJB, SOAP, Java RMI, JavaMail, JAAS,",
    "technologies JNDI, JNI, JAXP, JFC(SWING, AWT, Java 2D), JSF, JSTL, TLD, JPA, JAX-RPC,",
    "JAX-WS, JAX-RS, SAAJ, JTA, MyBatis",
    "UI Development HTML, CSS, JavaScript, AngularJS, Backbone.js, jQuery, Bootstrap, AJAX, JSON,",
    "technologies Adobe Flash",
    "Software development and TDD, SDLC, UML, Design Patterns, Unit testing, SOA, OOAD, EAI, Agile, Scrum,",
    "test methodologies Waterfall model",
    "Oracle, MongoDB, IBM DB2, SQL, NoSQL, MySQL, MS SQL Server, ODBC,",
    "Database management",
    "PL/SQL",
    "Apache Tomcat, OC4J, Oracle WebLogic Server, IBM WebSphere Application",
    "Web/Application Servers",
    "Server (WAS), JBoss (WildFly), Apache HTTP Server, IIS, GlassFish",
    "C, C++, Shell Scripting, Python, Perl, XML, XSD, DTD, XSL (XSLT, XSL-FO,",
    "Other Languages and XPath), SVG, ESB, Document Object Model, SAX, Wordpress, CORBA, SSO,",
    "Technologies REST, Uniface, Adobe Flex, Apache-CXF, Groovy, WSDL, IBM WebSphere",
    "software applications, Apache Zookeeper",
    "PROFESSIONAL EXPERIENCE:"
  ],
  "certifications": [],
  "tools": []
}